im_finished/__init__.py
im_finished/decorators/__init__.py
im_finished/decorators/send_text.py
im_finished/decorators/when_finished.py
im_finished/lib/__init__.py
im_finished/lib/sms.py
im_finished-1.0.0.dist-info/DESCRIPTION.rst
im_finished-1.0.0.dist-info/METADATA
im_finished-1.0.0.dist-info/RECORD
im_finished-1.0.0.dist-info/WHEEL
im_finished-1.0.0.dist-info/metadata.json
im_finished-1.0.0.dist-info/top_level.txt
