Metadata-Version: 2.0
Name: im-finished
Version: 1.0.0
Summary: Send text on function completion
Home-page: https://github.com/steinbachr/im-finished
Author: Bobby Steinbach
Author-email: steinbach.rj@gmail.com
License: MIT
Keywords: python decorators reporting sms twilio
Platform: UNKNOWN
Classifier: Development Status :: 3 - Alpha
Classifier: Intended Audience :: Developers
Classifier: Topic :: Software Development :: Libraries :: Python Modules
Classifier: License :: OSI Approved :: MIT License
Classifier: Programming Language :: Python :: 2
Classifier: Programming Language :: Python :: 2.6
Classifier: Programming Language :: Python :: 2.7
Classifier: Programming Language :: Python :: 3
Classifier: Programming Language :: Python :: 3.3
Requires-Dist: twilio (>=5,<6)
